csv_excel/__init__.py
csv_excel/__main__.py
csv_excel/csv_excel.py
csv_excel/vbaProject.bin
csv_excel/test/__init__.py
csv_excel/test/test_csv_excel.py
erichschroeter.csv_excel-0.1.0.dist-info/METADATA
erichschroeter.csv_excel-0.1.0.dist-info/WHEEL
erichschroeter.csv_excel-0.1.0.dist-info/top_level.txt
erichschroeter.csv_excel-0.1.0.dist-info/RECORD
