Metadata-Version: 2.2
Name: erichschroeter.csv_excel
Version: 0.1.0
Summary: A library to convert CSV files to Excel and back
Author-email: Erich Schroeter <erich.schroeter+pypi@gmail.com>
Project-URL: Homepage, https://github.com/erichschroeter/csv-excel
Project-URL: Issues, https://github.com/erichschroeter/csv-excel/issues
Classifier: Programming Language :: Python :: 3
Classifier: License :: OSI Approved :: MIT License
Classifier: Operating System :: OS Independent
Classifier: Topic :: Software Development :: Libraries :: Python Modules
Requires-Python: >=3.9
Requires-Dist: openpyxl==3.1.5
Requires-Dist: PyYAML==6.0.2
Requires-Dist: XlsxWriter==3.2.0
Provides-Extra: test
Requires-Dist: pytest==8.3.3; extra == "test"
